pyedo/__init__.py
pyedo/_info.py
pyedo/edo.py
pyedo/examples/StartUp.py
pyedo/examples/move_cartesianX.py
pyedo/examples/prog_cartesian.py
pyedo/examples/prog_circular.py
pyedo/examples/prog_circularX.py
pyedo/examples/prog_jogjoint.py
pyedo/examples/rodeo.py
pyedo_test_rws-0.8.dist-info/LICENSE
pyedo_test_rws-0.8.dist-info/METADATA
pyedo_test_rws-0.8.dist-info/WHEEL
pyedo_test_rws-0.8.dist-info/top_level.txt
pyedo_test_rws-0.8.dist-info/RECORD
